rantone/__init__.py
rantone/datasets.py
rantone/models.py
rantone/utils.py
rantone/visuals.py
rantone-0.5.dist-info/LICENCE.txt
rantone-0.5.dist-info/METADATA
rantone-0.5.dist-info/WHEEL
rantone-0.5.dist-info/top_level.txt
rantone-0.5.dist-info/RECORD
