Metadata-Version: 2.1
Name: rantone
Version: 0.5
Summary: This package contains deep learning utilities files
Author: Asiedu Henry
Author-email: sensork82@gmail.com
Classifier: Programming Language :: Python :: 3
Classifier: License :: OSI Approved :: MIT License
Classifier: Operating System :: OS Independent
License-File: LICENCE.txt
